LICENSE
MANIFEST.in
README.rst
setup.py
merethread/__init__.py
merethread/daemon.py
merethread/misc.py
merethread/samples.py
merethread/task.py
merethread/thread.py
merethread/utils.py
merethread/version.py
merethread.egg-info/PKG-INFO
merethread.egg-info/SOURCES.txt
merethread.egg-info/dependency_links.txt
merethread.egg-info/top_level.txt