Metadata-Version: 1.1
Name: merethread
Version: 0.1.2
Summary: Mere python threads, plus features
Home-page: https://github.com/shx2/merethread
Author: shx2
Author-email: shx222@gmail.com
License: MIT
Keywords: thread,multithreading,profiler
Platform: UNKNOWN
Classifier: Programming Language :: Python :: 3
Classifier: Development Status :: 3 - Alpha
Classifier: Intended Audience :: Developers
Classifier: Topic :: Software Development
Classifier: License :: OSI Approved :: MIT License
